<?xml version="1.0" encoding="UTF-8"?>
<Table>
  <Rows>
    <Row>
      <WIC_NUM>4371766-2008409146-1</WIC_NUM>
      <WIC_CASE_NUM>4371766</WIC_CASE_NUM>
      <WIC_DT_BEGIN>2022-05-23T00:00:00</WIC_DT_BEGIN>
      <WIC_DT_END>2022-05-27T00:00:00</WIC_DT_END>
      <WIC_STATUS>A</WIC_STATUS>
      <WIC_CD>1</WIC_CD>
      <WIC_CD_Name>Тимчасова непрацездатність внаслідок захворювання або травми, що не пов’язані з нещасним випадком на виробництві</WIC_CD_Name>
      <SIGN_ANLK_NARKOTIK_INTOXICATION>false</SIGN_ANLK_NARKOTIK_INTOXICATION>
      <VIOLATION_EXTENSION>false</VIOLATION_EXTENSION>
      <NP_SURNAME>СКЛЯРОВСЬКА</NP_SURNAME>
      <NP_NAME>ЛАРИСА</NP_NAME>
      <NP_PATRONYMIC>ДМИТРІВНА</NP_PATRONYMIC>
      <NP_NUMIDENT>1872604824</NP_NUMIDENT>
      <NP_DOC_NUM>ЕА690461</NP_DOC_NUM>
      <NP_PDT>1</NP_PDT>
    </Row>
    <Row>
      <WIC_NUM>4345295-2008399005-1</WIC_NUM>
      <WIC_CASE_NUM>4345295</WIC_CASE_NUM>
      <WIC_DT_BEGIN>2022-05-22T00:00:00</WIC_DT_BEGIN>
      <WIC_DT_END>2022-05-23T00:00:00</WIC_DT_END>
      <WIC_STATUS>A</WIC_STATUS>
      <WIC_CD>1</WIC_CD>
      <WIC_CD_Name>Тимчасова непрацездатність внаслідок захворювання або травми, що не пов’язані з нещасним випадком на виробництві</WIC_CD_Name>
      <SIGN_ANLK_NARKOTIK_INTOXICATION>false</SIGN_ANLK_NARKOTIK_INTOXICATION>
      <VIOLATION_EXTENSION>false</VIOLATION_EXTENSION>
      <NP_SURNAME>АКІМОВА</NP_SURNAME>
      <NP_NAME>СВІТЛАНА</NP_NAME>
      <NP_PATRONYMIC>ВАСИЛІВНА</NP_PATRONYMIC>
      <NP_NUMIDENT>2709120886</NP_NUMIDENT>
      <NP_DOC_NUM>ЕА737268</NP_DOC_NUM>
      <NP_PDT>1</NP_PDT>
    </Row>
    <Row>
      <WIC_NUM>4344682-2008398425-1</WIC_NUM>
      <WIC_CASE_NUM>4344682</WIC_CASE_NUM>
      <WIC_DT_BEGIN>2022-05-22T00:00:00</WIC_DT_BEGIN>
      <WIC_DT_END>2022-05-23T00:00:00</WIC_DT_END>
      <WIC_STATUS>A</WIC_STATUS>
      <WIC_CD>1</WIC_CD>
      <WIC_CD_Name>Тимчасова непрацездатність внаслідок захворювання або травми, що не пов’язані з нещасним випадком на виробництві</WIC_CD_Name>
      <SIGN_ANLK_NARKOTIK_INTOXICATION>false</SIGN_ANLK_NARKOTIK_INTOXICATION>
      <VIOLATION_EXTENSION>false</VIOLATION_EXTENSION>
      <NP_SURNAME>ШУЛЬГА</NP_SURNAME>
      <NP_NAME>ОЛЬГА</NP_NAME>
      <NP_PATRONYMIC>ОЛЕКСАНДРІВНА</NP_PATRONYMIC>
      <NP_NUMIDENT>2803102609</NP_NUMIDENT>
      <NP_DOC_NUM>ЕА032269</NP_DOC_NUM>
      <NP_PDT>1</NP_PDT>
    </Row>
    <Row>
      <WIC_NUM>4338880-2008387143-1</WIC_NUM>
      <WIC_CASE_NUM>4338880</WIC_CASE_NUM>
      <WIC_DT_BEGIN>2022-05-21T00:00:00</WIC_DT_BEGIN>
      <WIC_DT_END>2022-05-23T00:00:00</WIC_DT_END>
      <WIC_STATUS>A</WIC_STATUS>
      <WIC_CD>1</WIC_CD>
      <WIC_CD_Name>Тимчасова непрацездатність внаслідок захворювання або травми, що не пов’язані з нещасним випадком на виробництві</WIC_CD_Name>
      <SIGN_ANLK_NARKOTIK_INTOXICATION>false</SIGN_ANLK_NARKOTIK_INTOXICATION>
      <VIOLATION_EXTENSION>false</VIOLATION_EXTENSION>
      <NP_SURNAME>СКРИПНІЧЕНКО</NP_SURNAME>
      <NP_NAME>ОЛЬГА</NP_NAME>
      <NP_PATRONYMIC>СЕРГІЇВНА</NP_PATRONYMIC>
      <NP_NUMIDENT>2989610386</NP_NUMIDENT>
      <NP_DOC_NUM>ЕА561165</NP_DOC_NUM>
      <NP_PDT>1</NP_PDT>
    </Row>
    <Row>
      <WIC_NUM>4303487-2008354251-1</WIC_NUM>
      <WIC_CASE_NUM>4303487</WIC_CASE_NUM>
      <WIC_DT_BEGIN>2022-05-18T00:00:00</WIC_DT_BEGIN>
      <WIC_DT_END>2022-05-20T00:00:00</WIC_DT_END>
      <WIC_STATUS>A</WIC_STATUS>
      <WIC_CD>1</WIC_CD>
      <WIC_CD_Name>Тимчасова непрацездатність внаслідок захворювання або травми, що не пов’язані з нещасним випадком на виробництві</WIC_CD_Name>
      <SIGN_ANLK_NARKOTIK_INTOXICATION>false</SIGN_ANLK_NARKOTIK_INTOXICATION>
      <VIOLATION_EXTENSION>false</VIOLATION_EXTENSION>
      <NP_SURNAME>СКЛЯРОВСЬКА</NP_SURNAME>
      <NP_NAME>ЛАРИСА</NP_NAME>
      <NP_PATRONYMIC>ДМИТРІВНА</NP_PATRONYMIC>
      <NP_NUMIDENT>1872604824</NP_NUMIDENT>
      <NP_DOC_NUM>ЕА690461</NP_DOC_NUM>
      <NP_PDT>1</NP_PDT>
    </Row>
    <Row>
      <WIC_NUM>4345295-2008355431-1</WIC_NUM>
      <WIC_CASE_NUM>4345295</WIC_CASE_NUM>
      <WIC_DT_BEGIN>2022-05-17T00:00:00</WIC_DT_BEGIN>
      <WIC_DT_END>2022-05-21T00:00:00</WIC_DT_END>
      <WIC_STATUS>A</WIC_STATUS>
      <WIC_CD>1</WIC_CD>
      <WIC_CD_Name>Тимчасова непрацездатність внаслідок захворювання або травми, що не пов’язані з нещасним випадком на виробництві</WIC_CD_Name>
      <SIGN_ANLK_NARKOTIK_INTOXICATION>false</SIGN_ANLK_NARKOTIK_INTOXICATION>
      <VIOLATION_EXTENSION>false</VIOLATION_EXTENSION>
      <NP_SURNAME>АКІМОВА</NP_SURNAME>
      <NP_NAME>СВІТЛАНА</NP_NAME>
      <NP_PATRONYMIC>ВАСИЛІВНА</NP_PATRONYMIC>
      <NP_NUMIDENT>2709120886</NP_NUMIDENT>
      <NP_DOC_NUM>ЕА737268</NP_DOC_NUM>
      <NP_PDT>1</NP_PDT>
    </Row>
    <Row>
      <WIC_NUM>4344682-2008354279-1</WIC_NUM>
      <WIC_CASE_NUM>4344682</WIC_CASE_NUM>
      <WIC_DT_BEGIN>2022-05-17T00:00:00</WIC_DT_BEGIN>
      <WIC_DT_END>2022-05-21T00:00:00</WIC_DT_END>
      <WIC_STATUS>A</WIC_STATUS>
      <WIC_CD>1</WIC_CD>
      <WIC_CD_Name>Тимчасова непрацездатність внаслідок захворювання або травми, що не пов’язані з нещасним випадком на виробництві</WIC_CD_Name>
      <SIGN_ANLK_NARKOTIK_INTOXICATION>false</SIGN_ANLK_NARKOTIK_INTOXICATION>
      <VIOLATION_EXTENSION>false</VIOLATION_EXTENSION>
      <NP_SURNAME>ШУЛЬГА</NP_SURNAME>
      <NP_NAME>ОЛЬГА</NP_NAME>
      <NP_PATRONYMIC>ОЛЕКСАНДРІВНА</NP_PATRONYMIC>
      <NP_NUMIDENT>2803102609</NP_NUMIDENT>
      <NP_DOC_NUM>ЕА032269</NP_DOC_NUM>
      <NP_PDT>1</NP_PDT>
    </Row>
    <Row>
      <WIC_NUM>4240815-2008342465-1</WIC_NUM>
      <WIC_CASE_NUM>4240815</WIC_CASE_NUM>
      <WIC_DT_BEGIN>2022-05-17T00:00:00</WIC_DT_BEGIN>
      <WIC_DT_END>2022-05-24T00:00:00</WIC_DT_END>
      <WIC_STATUS>A</WIC_STATUS>
      <WIC_CD>1</WIC_CD>
      <WIC_CD_Name>Тимчасова непрацездатність внаслідок захворювання або травми, що не пов’язані з нещасним випадком на виробництві</WIC_CD_Name>
      <SIGN_ANLK_NARKOTIK_INTOXICATION>false</SIGN_ANLK_NARKOTIK_INTOXICATION>
      <VIOLATION_EXTENSION>false</VIOLATION_EXTENSION>
      <NP_SURNAME>МАТВЄЄВ</NP_SURNAME>
      <NP_NAME>ВІТАЛІЙ</NP_NAME>
      <NP_PATRONYMIC>ОЛЕКСАНДРОВИЧ</NP_PATRONYMIC>
      <NP_NUMIDENT>2981903471</NP_NUMIDENT>
      <NP_DOC_NUM>ЕА634646</NP_DOC_NUM>
      <NP_PDT>1</NP_PDT>
    </Row>
    <Row>
      <WIC_NUM>4338880-2008344271-1</WIC_NUM>
      <WIC_CASE_NUM>4338880</WIC_CASE_NUM>
      <WIC_DT_BEGIN>2022-05-16T00:00:00</WIC_DT_BEGIN>
      <WIC_DT_END>2022-05-20T00:00:00</WIC_DT_END>
      <WIC_STATUS>A</WIC_STATUS>
      <WIC_CD>1</WIC_CD>
      <WIC_CD_Name>Тимчасова непрацездатність внаслідок захворювання або травми, що не пов’язані з нещасним випадком на виробництві</WIC_CD_Name>
      <SIGN_ANLK_NARKOTIK_INTOXICATION>false</SIGN_ANLK_NARKOTIK_INTOXICATION>
      <VIOLATION_EXTENSION>false</VIOLATION_EXTENSION>
      <NP_SURNAME>СКРИПНІЧЕНКО</NP_SURNAME>
      <NP_NAME>ОЛЬГА</NP_NAME>
      <NP_PATRONYMIC>СЕРГІЇВНА</NP_PATRONYMIC>
      <NP_NUMIDENT>2989610386</NP_NUMIDENT>
      <NP_DOC_NUM>ЕА561165</NP_DOC_NUM>
      <NP_PDT>1</NP_PDT>
    </Row>
    <Row>
      <WIC_NUM>4183341-2008309897-1</WIC_NUM>
      <WIC_CASE_NUM>4183341</WIC_CASE_NUM>
      <WIC_DT_BEGIN>2022-05-12T00:00:00</WIC_DT_BEGIN>
      <WIC_DT_END>2022-05-23T00:00:00</WIC_DT_END>
      <WIC_STATUS>A</WIC_STATUS>
      <WIC_CD>1</WIC_CD>
      <WIC_CD_Name>Тимчасова непрацездатність внаслідок захворювання або травми, що не пов’язані з нещасним випадком на виробництві</WIC_CD_Name>
      <SIGN_ANLK_NARKOTIK_INTOXICATION>false</SIGN_ANLK_NARKOTIK_INTOXICATION>
      <VIOLATION_EXTENSION>false</VIOLATION_EXTENSION>
      <NP_SURNAME>САВКІНА</NP_SURNAME>
      <NP_NAME>НАТАЛЯ</NP_NAME>
      <NP_PATRONYMIC>МИКОЛАЇВНА</NP_PATRONYMIC>
      <NP_NUMIDENT>2605815065</NP_NUMIDENT>
      <NP_DOC_NUM>ЕА481166</NP_DOC_NUM>
      <NP_PDT>1</NP_PDT>
    </Row>
    <Row>
      <WIC_NUM>4105011-2008307281-1</WIC_NUM>
      <WIC_CASE_NUM>4105011</WIC_CASE_NUM>
      <WIC_DT_BEGIN>2022-05-12T00:00:00</WIC_DT_BEGIN>
      <WIC_DT_END>2022-05-16T00:00:00</WIC_DT_END>
      <WIC_STATUS>A</WIC_STATUS>
      <WIC_CD>1</WIC_CD>
      <WIC_CD_Name>Тимчасова непрацездатність внаслідок захворювання або травми, що не пов’язані з нещасним випадком на виробництві</WIC_CD_Name>
      <SIGN_ANLK_NARKOTIK_INTOXICATION>false</SIGN_ANLK_NARKOTIK_INTOXICATION>
      <VIOLATION_EXTENSION>false</VIOLATION_EXTENSION>
      <NP_SURNAME>БЕЛОГОР</NP_SURNAME>
      <NP_NAME>СЕРГІЙ</NP_NAME>
      <NP_PATRONYMIC>ВАСИЛЬОВИЧ</NP_PATRONYMIC>
      <NP_NUMIDENT>2276615970</NP_NUMIDENT>
      <NP_DOC_NUM>ЕА463459</NP_DOC_NUM>
      <NP_PDT>1</NP_PDT>
    </Row>
    <Row>
      <WIC_NUM>4299369-2008287042-1</WIC_NUM>
      <WIC_CASE_NUM>4299369</WIC_CASE_NUM>
      <WIC_DT_BEGIN>2022-05-11T00:00:00</WIC_DT_BEGIN>
      <WIC_DT_END>2022-05-14T00:00:00</WIC_DT_END>
      <WIC_STATUS>A</WIC_STATUS>
      <WIC_CD>1</WIC_CD>
      <WIC_CD_Name>Тимчасова непрацездатність внаслідок захворювання або травми, що не пов’язані з нещасним випадком на виробництві</WIC_CD_Name>
      <SIGN_ANLK_NARKOTIK_INTOXICATION>false</SIGN_ANLK_NARKOTIK_INTOXICATION>
      <VIOLATION_EXTENSION>false</VIOLATION_EXTENSION>
      <NP_SURNAME>РОМАЩЕНКО</NP_SURNAME>
      <NP_NAME>ІННА</NP_NAME>
      <NP_PATRONYMIC>АНАТОЛІЇВНА</NP_PATRONYMIC>
      <NP_NUMIDENT>2734014682</NP_NUMIDENT>
      <NP_DOC_NUM>004284258</NP_DOC_NUM>
      <NP_PDT>2</NP_PDT>
    </Row>
    <Row>
      <WIC_NUM>4312997-2008290749-1</WIC_NUM>
      <WIC_CASE_NUM>4312997</WIC_CASE_NUM>
      <WIC_DT_BEGIN>2022-05-10T00:00:00</WIC_DT_BEGIN>
      <WIC_DT_END>2022-05-17T00:00:00</WIC_DT_END>
      <WIC_STATUS>A</WIC_STATUS>
      <WIC_CD>1</WIC_CD>
      <WIC_CD_Name>Тимчасова непрацездатність внаслідок захворювання або травми, що не пов’язані з нещасним випадком на виробництві</WIC_CD_Name>
      <SIGN_ANLK_NARKOTIK_INTOXICATION>false</SIGN_ANLK_NARKOTIK_INTOXICATION>
      <VIOLATION_EXTENSION>false</VIOLATION_EXTENSION>
      <NP_SURNAME>РУДУМАН</NP_SURNAME>
      <NP_NAME>ЛЮДМИЛА</NP_NAME>
      <NP_PATRONYMIC>МИКОЛАЇВНА</NP_PATRONYMIC>
      <NP_NUMIDENT>2134711648</NP_NUMIDENT>
      <NP_DOC_NUM>ЕА885030</NP_DOC_NUM>
      <NP_PDT>1</NP_PDT>
    </Row>
    <Row>
      <WIC_NUM>4312921-2008290613-1</WIC_NUM>
      <WIC_CASE_NUM>4312921</WIC_CASE_NUM>
      <WIC_DT_BEGIN>2022-05-10T00:00:00</WIC_DT_BEGIN>
      <WIC_DT_END>2022-05-17T00:00:00</WIC_DT_END>
      <WIC_STATUS>A</WIC_STATUS>
      <WIC_CD>1</WIC_CD>
      <WIC_CD_Name>Тимчасова непрацездатність внаслідок захворювання або травми, що не пов’язані з нещасним випадком на виробництві</WIC_CD_Name>
      <SIGN_ANLK_NARKOTIK_INTOXICATION>false</SIGN_ANLK_NARKOTIK_INTOXICATION>
      <VIOLATION_EXTENSION>false</VIOLATION_EXTENSION>
      <NP_SURNAME>ЧЕРНЯВСЬКА</NP_SURNAME>
      <NP_NAME>ЛЕСЯ</NP_NAME>
      <NP_PATRONYMIC>ІВАНІВНА</NP_PATRONYMIC>
      <NP_NUMIDENT>2896204100</NP_NUMIDENT>
      <NP_DOC_NUM>ЕВ157483</NP_DOC_NUM>
      <NP_PDT>1</NP_PDT>
    </Row>
    <Row>
      <WIC_NUM>4309309-2008283371-1</WIC_NUM>
      <WIC_CASE_NUM>4309309</WIC_CASE_NUM>
      <WIC_DT_BEGIN>2022-05-10T00:00:00</WIC_DT_BEGIN>
      <WIC_DT_END>2022-05-17T00:00:00</WIC_DT_END>
      <WIC_STATUS>A</WIC_STATUS>
      <WIC_CD>1</WIC_CD>
      <WIC_CD_Name>Тимчасова непрацездатність внаслідок захворювання або травми, що не пов’язані з нещасним випадком на виробництві</WIC_CD_Name>
      <SIGN_ANLK_NARKOTIK_INTOXICATION>false</SIGN_ANLK_NARKOTIK_INTOXICATION>
      <VIOLATION_EXTENSION>false</VIOLATION_EXTENSION>
      <NP_SURNAME>КОРЖАВІНА</NP_SURNAME>
      <NP_NAME>АЛЬОНА</NP_NAME>
      <NP_PATRONYMIC>ВАСИЛІВНА</NP_PATRONYMIC>
      <NP_NUMIDENT>3160316621</NP_NUMIDENT>
      <NP_DOC_NUM>ЕВ118083</NP_DOC_NUM>
      <NP_PDT>1</NP_PDT>
    </Row>
    <Row>
      <WIC_NUM>4303487-2008273777-1</WIC_NUM>
      <WIC_CASE_NUM>4303487</WIC_CASE_NUM>
      <WIC_DT_BEGIN>2022-05-09T00:00:00</WIC_DT_BEGIN>
      <WIC_DT_END>2022-05-17T00:00:00</WIC_DT_END>
      <WIC_STATUS>A</WIC_STATUS>
      <WIC_CD>1</WIC_CD>
      <WIC_CD_Name>Тимчасова непрацездатність внаслідок захворювання або травми, що не пов’язані з нещасним випадком на виробництві</WIC_CD_Name>
      <SIGN_ANLK_NARKOTIK_INTOXICATION>false</SIGN_ANLK_NARKOTIK_INTOXICATION>
      <VIOLATION_EXTENSION>false</VIOLATION_EXTENSION>
      <NP_SURNAME>СКЛЯРОВСЬКА</NP_SURNAME>
      <NP_NAME>ЛАРИСА</NP_NAME>
      <NP_PATRONYMIC>ДМИТРІВНА</NP_PATRONYMIC>
      <NP_NUMIDENT>1872604824</NP_NUMIDENT>
      <NP_DOC_NUM>ЕА690461</NP_DOC_NUM>
      <NP_PDT>1</NP_PDT>
    </Row>
    <Row>
      <WIC_NUM>4299369-2008266716-1</WIC_NUM>
      <WIC_CASE_NUM>4299369</WIC_CASE_NUM>
      <WIC_DT_BEGIN>2022-05-07T00:00:00</WIC_DT_BEGIN>
      <WIC_DT_END>2022-05-10T00:00:00</WIC_DT_END>
      <WIC_STATUS>A</WIC_STATUS>
      <WIC_CD>1</WIC_CD>
      <WIC_CD_Name>Тимчасова непрацездатність внаслідок захворювання або травми, що не пов’язані з нещасним випадком на виробництві</WIC_CD_Name>
      <SIGN_ANLK_NARKOTIK_INTOXICATION>false</SIGN_ANLK_NARKOTIK_INTOXICATION>
      <VIOLATION_EXTENSION>false</VIOLATION_EXTENSION>
      <NP_SURNAME>РОМАЩЕНКО</NP_SURNAME>
      <NP_NAME>ІННА</NP_NAME>
      <NP_PATRONYMIC>АНАТОЛІЇВНА</NP_PATRONYMIC>
      <NP_NUMIDENT>2734014682</NP_NUMIDENT>
      <NP_DOC_NUM>004284258</NP_DOC_NUM>
      <NP_PDT>2</NP_PDT>
    </Row>
    <Row>
      <WIC_NUM>4264644-2008242879-1</WIC_NUM>
      <WIC_CASE_NUM>4264644</WIC_CASE_NUM>
      <WIC_DT_BEGIN>2022-05-07T00:00:00</WIC_DT_BEGIN>
      <WIC_DT_END>2022-05-30T00:00:00</WIC_DT_END>
      <WIC_STATUS>A</WIC_STATUS>
      <WIC_CD>1</WIC_CD>
      <WIC_CD_Name>Тимчасова непрацездатність внаслідок захворювання або травми, що не пов’язані з нещасним випадком на виробництві</WIC_CD_Name>
      <SIGN_ANLK_NARKOTIK_INTOXICATION>false</SIGN_ANLK_NARKOTIK_INTOXICATION>
      <VIOLATION_EXTENSION>false</VIOLATION_EXTENSION>
      <NP_SURNAME>ДЖУРА</NP_SURNAME>
      <NP_NAME>ВАЛЕНТИНА</NP_NAME>
      <NP_PATRONYMIC>МИКОЛАІВНА</NP_PATRONYMIC>
      <NP_NUMIDENT>2257305307</NP_NUMIDENT>
      <NP_DOC_NUM>ЕА634790</NP_DOC_NUM>
      <NP_PDT>1</NP_PDT>
    </Row>
    <Row>
      <WIC_NUM>4288031-2008239801-1</WIC_NUM>
      <WIC_CASE_NUM>4288031</WIC_CASE_NUM>
      <WIC_DT_BEGIN>2022-05-05T00:00:00</WIC_DT_BEGIN>
      <WIC_DT_END>2022-05-11T00:00:00</WIC_DT_END>
      <WIC_STATUS>A</WIC_STATUS>
      <WIC_CD>1</WIC_CD>
      <WIC_CD_Name>Тимчасова непрацездатність внаслідок захворювання або травми, що не пов’язані з нещасним випадком на виробництві</WIC_CD_Name>
      <SIGN_ANLK_NARKOTIK_INTOXICATION>false</SIGN_ANLK_NARKOTIK_INTOXICATION>
      <VIOLATION_EXTENSION>false</VIOLATION_EXTENSION>
      <NP_SURNAME>ШВЕДЧЕНКО</NP_SURNAME>
      <NP_NAME>ОЛЬГА</NP_NAME>
      <NP_PATRONYMIC>ВАСИЛІВНА</NP_PATRONYMIC>
      <NP_NUMIDENT>3152021960</NP_NUMIDENT>
      <NP_DOC_NUM>002788364</NP_DOC_NUM>
      <NP_PDT>2</NP_PDT>
    </Row>
    <Row>
      <WIC_NUM>4234935-2008187746-1</WIC_NUM>
      <WIC_CASE_NUM>4234935</WIC_CASE_NUM>
      <WIC_DT_BEGIN>2022-05-03T00:00:00</WIC_DT_BEGIN>
      <WIC_DT_END>2022-05-28T00:00:00</WIC_DT_END>
      <WIC_STATUS>A</WIC_STATUS>
      <WIC_CD>1</WIC_CD>
      <WIC_CD_Name>Тимчасова непрацездатність внаслідок захворювання або травми, що не пов’язані з нещасним випадком на виробництві</WIC_CD_Name>
      <SIGN_ANLK_NARKOTIK_INTOXICATION>false</SIGN_ANLK_NARKOTIK_INTOXICATION>
      <VIOLATION_EXTENSION>false</VIOLATION_EXTENSION>
      <NP_SURNAME>ВОРОНА</NP_SURNAME>
      <NP_NAME>ТЕТЯНА</NP_NAME>
      <NP_PATRONYMIC>АНАТОЛІЇВНА</NP_PATRONYMIC>
      <NP_NUMIDENT>2509303482</NP_NUMIDENT>
      <NP_DOC_NUM>ЕА634615</NP_DOC_NUM>
      <NP_PDT>1</NP_PDT>
    </Row>
    <Row>
      <WIC_NUM>4268285-2008207201-1</WIC_NUM>
      <WIC_CASE_NUM>4268285</WIC_CASE_NUM>
      <WIC_DT_BEGIN>2022-05-02T00:00:00</WIC_DT_BEGIN>
      <WIC_DT_END>2022-05-07T00:00:00</WIC_DT_END>
      <WIC_STATUS>A</WIC_STATUS>
      <WIC_CD>1</WIC_CD>
      <WIC_CD_Name>Тимчасова непрацездатність внаслідок захворювання або травми, що не пов’язані з нещасним випадком на виробництві</WIC_CD_Name>
      <SIGN_ANLK_NARKOTIK_INTOXICATION>false</SIGN_ANLK_NARKOTIK_INTOXICATION>
      <VIOLATION_EXTENSION>false</VIOLATION_EXTENSION>
      <NP_SURNAME>ЗАХАРОВ</NP_SURNAME>
      <NP_NAME>ЮРІЙ</NP_NAME>
      <NP_PATRONYMIC>ВАЛЕНТИНОВИЧ</NP_PATRONYMIC>
      <NP_NUMIDENT>2198309730</NP_NUMIDENT>
      <NP_DOC_NUM>ЕА967775</NP_DOC_NUM>
      <NP_PDT>1</NP_PDT>
    </Row>
    <Row>
      <WIC_NUM>4264644-2008200910-1</WIC_NUM>
      <WIC_CASE_NUM>4264644</WIC_CASE_NUM>
      <WIC_DT_BEGIN>2022-05-01T00:00:00</WIC_DT_BEGIN>
      <WIC_DT_END>2022-05-06T00:00:00</WIC_DT_END>
      <WIC_STATUS>A</WIC_STATUS>
      <WIC_CD>1</WIC_CD>
      <WIC_CD_Name>Тимчасова непрацездатність внаслідок захворювання або травми, що не пов’язані з нещасним випадком на виробництві</WIC_CD_Name>
      <SIGN_ANLK_NARKOTIK_INTOXICATION>false</SIGN_ANLK_NARKOTIK_INTOXICATION>
      <VIOLATION_EXTENSION>false</VIOLATION_EXTENSION>
      <NP_SURNAME>ДЖУРА</NP_SURNAME>
      <NP_NAME>ВАЛЕНТИНА</NP_NAME>
      <NP_PATRONYMIC>МИКОЛАІВНА</NP_PATRONYMIC>
      <NP_NUMIDENT>2257305307</NP_NUMIDENT>
      <NP_DOC_NUM>ЕА634790</NP_DOC_NUM>
      <NP_PDT>1</NP_PDT>
    </Row>
    <Row>
      <WIC_NUM>4236952-2008214640-1</WIC_NUM>
      <WIC_CASE_NUM>4236952</WIC_CASE_NUM>
      <WIC_DT_BEGIN>2022-04-30T00:00:00</WIC_DT_BEGIN>
      <WIC_DT_END>2022-05-06T00:00:00</WIC_DT_END>
      <WIC_STATUS>A</WIC_STATUS>
      <WIC_CD>1</WIC_CD>
      <WIC_CD_Name>Тимчасова непрацездатність внаслідок захворювання або травми, що не пов’язані з нещасним випадком на виробництві</WIC_CD_Name>
      <SIGN_ANLK_NARKOTIK_INTOXICATION>false</SIGN_ANLK_NARKOTIK_INTOXICATION>
      <VIOLATION_EXTENSION>false</VIOLATION_EXTENSION>
      <NP_SURNAME>ДЕМКІВ</NP_SURNAME>
      <NP_NAME>МАРИНА</NP_NAME>
      <NP_PATRONYMIC>ОЛЕКСАНДРІВНА</NP_PATRONYMIC>
      <NP_NUMIDENT>2480608586</NP_NUMIDENT>
      <NP_DOC_NUM>СА901462</NP_DOC_NUM>
      <NP_PDT>1</NP_PDT>
    </Row>
    <Row>
      <WIC_NUM>4260000-2008188435-1</WIC_NUM>
      <WIC_CASE_NUM>4260000</WIC_CASE_NUM>
      <WIC_DT_BEGIN>2022-04-29T00:00:00</WIC_DT_BEGIN>
      <WIC_DT_END>2022-05-13T00:00:00</WIC_DT_END>
      <WIC_STATUS>A</WIC_STATUS>
      <WIC_CD>1</WIC_CD>
      <WIC_CD_Name>Тимчасова непрацездатність внаслідок захворювання або травми, що не пов’язані з нещасним випадком на виробництві</WIC_CD_Name>
      <SIGN_ANLK_NARKOTIK_INTOXICATION>false</SIGN_ANLK_NARKOTIK_INTOXICATION>
      <VIOLATION_EXTENSION>false</VIOLATION_EXTENSION>
      <NP_SURNAME>ВАСИЛЕНКО</NP_SURNAME>
      <NP_NAME>НАТАЛІЯ</NP_NAME>
      <NP_PATRONYMIC>ВАСИЛІВНА</NP_PATRONYMIC>
      <NP_NUMIDENT>2659909708</NP_NUMIDENT>
      <NP_DOC_NUM>ЕА561376</NP_DOC_NUM>
      <NP_PDT>1</NP_PDT>
    </Row>
    <Row>
      <WIC_NUM>4124557-2008177258-1</WIC_NUM>
      <WIC_CASE_NUM>4124557</WIC_CASE_NUM>
      <WIC_DT_BEGIN>2022-04-28T00:00:00</WIC_DT_BEGIN>
      <WIC_DT_END>2022-05-27T00:00:00</WIC_DT_END>
      <WIC_STATUS>A</WIC_STATUS>
      <WIC_CD>1</WIC_CD>
      <WIC_CD_Name>Тимчасова непрацездатність внаслідок захворювання або травми, що не пов’язані з нещасним випадком на виробництві</WIC_CD_Name>
      <SIGN_ANLK_NARKOTIK_INTOXICATION>false</SIGN_ANLK_NARKOTIK_INTOXICATION>
      <VIOLATION_EXTENSION>false</VIOLATION_EXTENSION>
      <NP_SURNAME>СІРЧЕНКО</NP_SURNAME>
      <NP_NAME>АНТОНІНА</NP_NAME>
      <NP_PATRONYMIC>МИКОЛАІВНА</NP_PATRONYMIC>
      <NP_NUMIDENT>2360304043</NP_NUMIDENT>
      <NP_DOC_NUM>ЕА773552</NP_DOC_NUM>
      <NP_PDT>1</NP_PDT>
    </Row>
    <Row>
      <WIC_NUM>4247914-2008163664-1</WIC_NUM>
      <WIC_CASE_NUM>4247914</WIC_CASE_NUM>
      <WIC_DT_BEGIN>2022-04-25T00:00:00</WIC_DT_BEGIN>
      <WIC_DT_END>2022-05-06T00:00:00</WIC_DT_END>
      <WIC_STATUS>A</WIC_STATUS>
      <WIC_CD>1</WIC_CD>
      <WIC_CD_Name>Тимчасова непрацездатність внаслідок захворювання або травми, що не пов’язані з нещасним випадком на виробництві</WIC_CD_Name>
      <SIGN_ANLK_NARKOTIK_INTOXICATION>false</SIGN_ANLK_NARKOTIK_INTOXICATION>
      <VIOLATION_EXTENSION>false</VIOLATION_EXTENSION>
      <NP_SURNAME>КРАТ</NP_SURNAME>
      <NP_NAME>ІРИНА</NP_NAME>
      <NP_PATRONYMIC>ВОЛОДИМИРІВНА</NP_PATRONYMIC>
      <NP_NUMIDENT>2736216567</NP_NUMIDENT>
      <NP_DOC_NUM>004141723</NP_DOC_NUM>
      <NP_PDT>2</NP_PDT>
    </Row>
    <Row>
      <WIC_NUM>4240815-2008151093-1</WIC_NUM>
      <WIC_CASE_NUM>4240815</WIC_CASE_NUM>
      <WIC_DT_BEGIN>2022-04-25T00:00:00</WIC_DT_BEGIN>
      <WIC_DT_END>2022-05-16T00:00:00</WIC_DT_END>
      <WIC_STATUS>A</WIC_STATUS>
      <WIC_CD>1</WIC_CD>
      <WIC_CD_Name>Тимчасова непрацездатність внаслідок захворювання або травми, що не пов’язані з нещасним випадком на виробництві</WIC_CD_Name>
      <SIGN_ANLK_NARKOTIK_INTOXICATION>false</SIGN_ANLK_NARKOTIK_INTOXICATION>
      <VIOLATION_EXTENSION>false</VIOLATION_EXTENSION>
      <NP_SURNAME>МАТВЄЄВ</NP_SURNAME>
      <NP_NAME>ВІТАЛІЙ</NP_NAME>
      <NP_PATRONYMIC>ОЛЕКСАНДРОВИЧ</NP_PATRONYMIC>
      <NP_NUMIDENT>2981903471</NP_NUMIDENT>
      <NP_DOC_NUM>ЕА634646</NP_DOC_NUM>
      <NP_PDT>1</NP_PDT>
    </Row>
    <Row>
      <WIC_NUM>4237415-2008145068-2</WIC_NUM>
      <WIC_CASE_NUM>4237415</WIC_CASE_NUM>
      <WIC_DT_BEGIN>2022-04-25T00:00:00</WIC_DT_BEGIN>
      <WIC_DT_END>2022-05-04T00:00:00</WIC_DT_END>
      <WIC_STATUS>A</WIC_STATUS>
      <WIC_CD>1</WIC_CD>
      <WIC_CD_Name>Тимчасова непрацездатність внаслідок захворювання або травми, що не пов’язані з нещасним випадком на виробництві</WIC_CD_Name>
      <SIGN_ANLK_NARKOTIK_INTOXICATION>false</SIGN_ANLK_NARKOTIK_INTOXICATION>
      <VIOLATION_EXTENSION>false</VIOLATION_EXTENSION>
      <NP_SURNAME>БАСКАКОВ</NP_SURNAME>
      <NP_NAME>ОЛЕКСАНДР</NP_NAME>
      <NP_PATRONYMIC>ГЛІБОВИЧ</NP_PATRONYMIC>
      <NP_NUMIDENT>2792422458</NP_NUMIDENT>
      <NP_DOC_NUM>ЕА896356</NP_DOC_NUM>
      <NP_PDT>1</NP_PDT>
    </Row>
    <Row>
      <WIC_NUM>4234935-2008139917-1</WIC_NUM>
      <WIC_CASE_NUM>4234935</WIC_CASE_NUM>
      <WIC_DT_BEGIN>2022-04-23T00:00:00</WIC_DT_BEGIN>
      <WIC_DT_END>2022-05-02T00:00:00</WIC_DT_END>
      <WIC_STATUS>A</WIC_STATUS>
      <WIC_CD>1</WIC_CD>
      <WIC_CD_Name>Тимчасова непрацездатність внаслідок захворювання або травми, що не пов’язані з нещасним випадком на виробництві</WIC_CD_Name>
      <SIGN_ANLK_NARKOTIK_INTOXICATION>false</SIGN_ANLK_NARKOTIK_INTOXICATION>
      <VIOLATION_EXTENSION>false</VIOLATION_EXTENSION>
      <NP_SURNAME>ВОРОНА</NP_SURNAME>
      <NP_NAME>ТЕТЯНА</NP_NAME>
      <NP_PATRONYMIC>АНАТОЛІЇВНА</NP_PATRONYMIC>
      <NP_NUMIDENT>2509303482</NP_NUMIDENT>
      <NP_DOC_NUM>ЕА634615</NP_DOC_NUM>
      <NP_PDT>1</NP_PDT>
    </Row>
    <Row>
      <WIC_NUM>4105011-2008122485-1</WIC_NUM>
      <WIC_CASE_NUM>4105011</WIC_CASE_NUM>
      <WIC_DT_BEGIN>2022-04-22T00:00:00</WIC_DT_BEGIN>
      <WIC_DT_END>2022-05-11T00:00:00</WIC_DT_END>
      <WIC_STATUS>A</WIC_STATUS>
      <WIC_CD>1</WIC_CD>
      <WIC_CD_Name>Тимчасова непрацездатність внаслідок захворювання або травми, що не пов’язані з нещасним випадком на виробництві</WIC_CD_Name>
      <SIGN_ANLK_NARKOTIK_INTOXICATION>false</SIGN_ANLK_NARKOTIK_INTOXICATION>
      <VIOLATION_EXTENSION>false</VIOLATION_EXTENSION>
      <NP_SURNAME>БЕЛОГОР</NP_SURNAME>
      <NP_NAME>СЕРГІЙ</NP_NAME>
      <NP_PATRONYMIC>ВАСИЛЬОВИЧ</NP_PATRONYMIC>
      <NP_NUMIDENT>2276615970</NP_NUMIDENT>
      <NP_DOC_NUM>ЕА463459</NP_DOC_NUM>
      <NP_PDT>1</NP_PDT>
    </Row>
    <Row>
      <WIC_NUM>4069987-2008070624-2</WIC_NUM>
      <WIC_CASE_NUM>4069987</WIC_CASE_NUM>
      <WIC_DT_BEGIN>2022-04-16T00:00:00</WIC_DT_BEGIN>
      <WIC_DT_END>2022-05-06T00:00:00</WIC_DT_END>
      <WIC_STATUS>A</WIC_STATUS>
      <WIC_CD>1</WIC_CD>
      <WIC_CD_Name>Тимчасова непрацездатність внаслідок захворювання або травми, що не пов’язані з нещасним випадком на виробництві</WIC_CD_Name>
      <SIGN_ANLK_NARKOTIK_INTOXICATION>false</SIGN_ANLK_NARKOTIK_INTOXICATION>
      <VIOLATION_EXTENSION>false</VIOLATION_EXTENSION>
      <NP_SURNAME>МАЗУР</NP_SURNAME>
      <NP_NAME>СЕРГІЙ</NP_NAME>
      <NP_PATRONYMIC>ВОЛОДИМИРОВИЧ</NP_PATRONYMIC>
      <NP_NUMIDENT>2539206270</NP_NUMIDENT>
      <NP_DOC_NUM>ЕА646910</NP_DOC_NUM>
      <NP_PDT>1</NP_PDT>
    </Row>
    <Row>
      <WIC_NUM>4183341-2008034431-1</WIC_NUM>
      <WIC_CASE_NUM>4183341</WIC_CASE_NUM>
      <WIC_DT_BEGIN>2022-04-12T00:00:00</WIC_DT_BEGIN>
      <WIC_DT_END>2022-05-11T00:00:00</WIC_DT_END>
      <WIC_STATUS>A</WIC_STATUS>
      <WIC_CD>1</WIC_CD>
      <WIC_CD_Name>Тимчасова непрацездатність внаслідок захворювання або травми, що не пов’язані з нещасним випадком на виробництві</WIC_CD_Name>
      <SIGN_ANLK_NARKOTIK_INTOXICATION>false</SIGN_ANLK_NARKOTIK_INTOXICATION>
      <VIOLATION_EXTENSION>false</VIOLATION_EXTENSION>
      <NP_SURNAME>САВКІНА</NP_SURNAME>
      <NP_NAME>НАТАЛЯ</NP_NAME>
      <NP_PATRONYMIC>МИКОЛАЇВНА</NP_PATRONYMIC>
      <NP_NUMIDENT>2605815065</NP_NUMIDENT>
      <NP_DOC_NUM>ЕА481166</NP_DOC_NUM>
      <NP_PDT>1</NP_PDT>
    </Row>
  </Rows>
</Table>